mopaint/__init__.py
mopaint/static/draw.css
mopaint/static/draw.js
mopaint/static/styles.css
mopaint-0.4.1.dist-info/METADATA
mopaint-0.4.1.dist-info/WHEEL
mopaint-0.4.1.dist-info/licenses/LICENSE
mopaint-0.4.1.dist-info/RECORD
