Metadata-Version: 2.4
Name: mopaint
Version: 0.4.1
Summary: Paint for marimo
Project-URL: Homepage, https://github.com/koaning/mopaint
Project-URL: Documentation, https://koaning.github.io/mopaint/
Project-URL: Repository, https://github.com/koaning/mopaint
Project-URL: Issues, https://github.com/koaning/mopaint/issues
Author: Vincent D. Warmerdam
License: MIT License
License-File: LICENSE
Classifier: Intended Audience :: Developers
Classifier: Intended Audience :: Science/Research
Classifier: License :: OSI Approved :: MIT License
Classifier: Programming Language :: Python :: 3
Classifier: Programming Language :: Python :: 3.8
Classifier: Programming Language :: Python :: 3.9
Classifier: Programming Language :: Python :: 3.10
Classifier: Programming Language :: Python :: 3.11
Classifier: Programming Language :: Python :: 3.12
Classifier: Programming Language :: Python :: 3.13
Classifier: Programming Language :: Python :: 3.14
Classifier: Topic :: Scientific/Engineering
Requires-Python: >=3.8
Requires-Dist: anywidget>=0.9.2
Requires-Dist: protobuf>=5.29.5
Provides-Extra: dev
Requires-Dist: marimo; extra == 'dev'
Requires-Dist: mohtml; extra == 'dev'
Requires-Dist: pillow>=9.0; extra == 'dev'
Requires-Dist: pytest>=7.0; extra == 'dev'
